disboxpy/__init__.py
disboxpy/disbox.py
disboxpy/utils.py
disboxpy-1.0.0rc0.dist-info/METADATA
disboxpy-1.0.0rc0.dist-info/WHEEL
disboxpy-1.0.0rc0.dist-info/top_level.txt
disboxpy-1.0.0rc0.dist-info/RECORD
