Metadata-Version: 2.1
Name: disboxpy
Version: 1.0.0rc0
Summary: A perfectly asynchronous DisBox API framework.
Author: inREZy
Author-email: xardmax2000@gmail.com
Requires-Dist: httpx
